<?xml version="1.0" ?>
<Root>
    <TestCase name="testPartialFlush_2">
        <Resource name="output">
            <![CDATA[Cache state before flush:
*Segment Header
Schema:[FoodMart]
Checksum:[adc67095ea588fb8ef5cc174a3f74b7a]
Cube:[Sales]
Measure:[Unit Sales]
Axes:[
    {`time_by_day`.`the_year`=('1997')}
    {`customer`.`gender`=('M')}]
Excluded Regions:[]
Compound Predicates:[]
ID:[bb4f14dce5f5107ae653289ea3fdde0f286c6843e9af9b4fd560361189562b45]


Cache state after flush:
*Segment Header
Schema:[FoodMart]
Checksum:[adc67095ea588fb8ef5cc174a3f74b7a]
Cube:[Sales]
Measure:[Unit Sales]
Axes:[
    {`time_by_day`.`the_year`=('1997')}
    {`customer`.`gender`=('M')}]
Excluded Regions:[]
Compound Predicates:[]
ID:[bb4f14dce5f5107ae653289ea3fdde0f286c6843e9af9b4fd560361189562b45]


]]>
        </Resource>
        <Resource name="output2">
            <![CDATA[Cache state before flush:
*Segment Header
Schema:[FoodMart]
Checksum:[adc67095ea588fb8ef5cc174a3f74b7a]
Cube:[Sales]
Measure:[Unit Sales]
Axes:[
    {`time_by_day`.`the_year`=('1997')}
    {`customer`.`gender`=('M')}]
Excluded Regions:[]
Compound Predicates:[]
ID:[bb4f14dce5f5107ae653289ea3fdde0f286c6843e9af9b4fd560361189562b45]


discard segment - it cannot be constrained and maintain consistency:
*Segment Header
Schema:[FoodMart]
Checksum:[adc67095ea588fb8ef5cc174a3f74b7a]
Cube:[Sales]
Measure:[Unit Sales]
Axes:[
    {`time_by_day`.`the_year`=('1997')}
    {`customer`.`gender`=('M')}]
Excluded Regions:[]
Compound Predicates:[]
ID:[bb4f14dce5f5107ae653289ea3fdde0f286c6843e9af9b4fd560361189562b45]

Cache state after flush:

]]>
        </Resource>
    </TestCase>
    <TestCase name="testMondrian1094">
        <Resource name="output">
            <![CDATA[Cache state before flush:
*Segment Header
Schema:[FoodMart]
Checksum:[9cca66327439577753dd5c3144ab59b5]
Cube:[Sales]
Measure:[Unit Sales]
Axes:[
    {store.store_country=('USA')}
    {time_by_day.the_year=('1997')}]
Excluded Regions:[]
Compound Predicates:[]
ID:[247b8a6562d3147e730bdca37fb2d0f72432a7fdf660466e2a52fdbda2458f28]


discard segment - it cannot be constrained and maintain consistency:
*Segment Header
Schema:[FoodMart]
Checksum:[9cca66327439577753dd5c3144ab59b5]
Cube:[Sales]
Measure:[Unit Sales]
Axes:[
    {store.store_country=('USA')}
    {time_by_day.the_year=('1997')}]
Excluded Regions:[]
Compound Predicates:[]
ID:[247b8a6562d3147e730bdca37fb2d0f72432a7fdf660466e2a52fdbda2458f28]

Cache state after flush:

]]>
        </Resource>
    </TestCase>
    <TestCase name="testPartialFlush">
        <Resource name="output">
            <![CDATA[Cache state before flush:
*Segment Header
Schema:[FoodMart]
Checksum:[adc67095ea588fb8ef5cc174a3f74b7a]
Cube:[Sales]
Measure:[Unit Sales]
Axes:[
    {`time_by_day`.`the_year`=(*)}
    {`time_by_day`.`quarter`=(*)}
    {`product_class`.`product_family`=(*)}]
Excluded Regions:[]
Compound Predicates:[]
ID:[8a3939757ec208163e5055273052b42dff2d30427ba96d9dbc847a30b02bc33d]

*Segment Header
Schema:[FoodMart]
Checksum:[adc67095ea588fb8ef5cc174a3f74b7a]
Cube:[Sales]
Measure:[Unit Sales]
Axes:[
    {`time_by_day`.`the_year`=(*)}
    {`time_by_day`.`month_of_year`=(*)}
    {`product_class`.`product_family`=(*)}]
Excluded Regions:[]
Compound Predicates:[]
ID:[96d7e3c62da4423e048b87cb83dd06fc3b19223d8f9d9c95e9169f292dd29cb5]

*Segment Header
Schema:[FoodMart]
Checksum:[adc67095ea588fb8ef5cc174a3f74b7a]
Cube:[Sales]
Measure:[Unit Sales]
Axes:[
    {`time_by_day`.`the_year`=(*)}
    {`product_class`.`product_family`=(*)}]
Excluded Regions:[]
Compound Predicates:[]
ID:[4a078bc2e0f7d362dc7b9f3ff775166cc40ba5a040af5fe11c43d8c1a4d8a832]


Cache state after flush:
*Segment Header
Schema:[FoodMart]
Checksum:[adc67095ea588fb8ef5cc174a3f74b7a]
Cube:[Sales]
Measure:[Unit Sales]
Axes:[
    {`time_by_day`.`the_year`=(*)}
    {`time_by_day`.`quarter`=(*)}
    {`product_class`.`product_family`=(*)}]
Excluded Regions:[
    {`time_by_day`.`quarter`=('Q1')}
    {`time_by_day`.`the_year`=('1997')}]
Compound Predicates:[]
ID:[9f50b66f4b4ec752bffb517748da678f9a27b778348ebac17d56026b7a4c5322]

*Segment Header
Schema:[FoodMart]
Checksum:[adc67095ea588fb8ef5cc174a3f74b7a]
Cube:[Sales]
Measure:[Unit Sales]
Axes:[
    {`time_by_day`.`the_year`=(*)}
    {`time_by_day`.`month_of_year`=(*)}
    {`product_class`.`product_family`=(*)}]
Excluded Regions:[
    {`time_by_day`.`the_year`=('1997')}]
Compound Predicates:[]
ID:[fe48ec3f27eaa745d01f2fbecbd7d4b402919c0c8284df1fde387b2335346af6]

*Segment Header
Schema:[FoodMart]
Checksum:[adc67095ea588fb8ef5cc174a3f74b7a]
Cube:[Sales]
Measure:[Unit Sales]
Axes:[
    {`time_by_day`.`the_year`=(*)}
    {`product_class`.`product_family`=(*)}]
Excluded Regions:[
    {`time_by_day`.`the_year`=('1997')}]
Compound Predicates:[]
ID:[4da974e2956637bee48be7ef4b6a766d92ba009ca69a4a7a5583d49cd4c8943c]


]]>
        </Resource>
        <Resource name="output2">
            <![CDATA[Cache state before flush:
*Segment Header
Schema:[FoodMart]
Checksum:[adc67095ea588fb8ef5cc174a3f74b7a]
Cube:[Sales]
Measure:[Unit Sales]
Axes:[
    {`time_by_day`.`the_year`=(*)}
    {`time_by_day`.`quarter`=(*)}
    {`product_class`.`product_family`=(*)}]
Excluded Regions:[
    {`time_by_day`.`quarter`=('Q1')}
    {`time_by_day`.`the_year`=('1997')}]
Compound Predicates:[]
ID:[9f50b66f4b4ec752bffb517748da678f9a27b778348ebac17d56026b7a4c5322]

*Segment Header
Schema:[FoodMart]
Checksum:[adc67095ea588fb8ef5cc174a3f74b7a]
Cube:[Sales]
Measure:[Unit Sales]
Axes:[
    {`time_by_day`.`the_year`=(*)}
    {`time_by_day`.`month_of_year`=(*)}
    {`product_class`.`product_family`=(*)}]
Excluded Regions:[
    {`time_by_day`.`the_year`=('1997')}]
Compound Predicates:[]
ID:[fe48ec3f27eaa745d01f2fbecbd7d4b402919c0c8284df1fde387b2335346af6]

*Segment Header
Schema:[FoodMart]
Checksum:[adc67095ea588fb8ef5cc174a3f74b7a]
Cube:[Sales]
Measure:[Unit Sales]
Axes:[
    {`time_by_day`.`the_year`=(*)}
    {`product_class`.`product_family`=(*)}]
Excluded Regions:[
    {`time_by_day`.`the_year`=('1997')}]
Compound Predicates:[]
ID:[4da974e2956637bee48be7ef4b6a766d92ba009ca69a4a7a5583d49cd4c8943c]


Cache state after flush:
*Segment Header
Schema:[FoodMart]
Checksum:[adc67095ea588fb8ef5cc174a3f74b7a]
Cube:[Sales]
Measure:[Unit Sales]
Axes:[
    {`time_by_day`.`the_year`=(*)}
    {`time_by_day`.`quarter`=(*)}
    {`product_class`.`product_family`=(*)}]
Excluded Regions:[
    {`time_by_day`.`quarter`=('Q1')}
    {`time_by_day`.`the_year`=('1997')}]
Compound Predicates:[]
ID:[9f50b66f4b4ec752bffb517748da678f9a27b778348ebac17d56026b7a4c5322]

*Segment Header
Schema:[FoodMart]
Checksum:[adc67095ea588fb8ef5cc174a3f74b7a]
Cube:[Sales]
Measure:[Unit Sales]
Axes:[
    {`time_by_day`.`the_year`=(*)}
    {`time_by_day`.`month_of_year`=(*)}
    {`product_class`.`product_family`=(*)}]
Excluded Regions:[
    {`time_by_day`.`the_year`=('1997')}]
Compound Predicates:[]
ID:[fe48ec3f27eaa745d01f2fbecbd7d4b402919c0c8284df1fde387b2335346af6]

*Segment Header
Schema:[FoodMart]
Checksum:[adc67095ea588fb8ef5cc174a3f74b7a]
Cube:[Sales]
Measure:[Unit Sales]
Axes:[
    {`time_by_day`.`the_year`=(*)}
    {`product_class`.`product_family`=(*)}]
Excluded Regions:[
    {`time_by_day`.`the_year`=('1997')}]
Compound Predicates:[]
ID:[4da974e2956637bee48be7ef4b6a766d92ba009ca69a4a7a5583d49cd4c8943c]


]]>
        </Resource>
        <Resource name="output3">
            <![CDATA[Cache state before flush:
*Segment Header
Schema:[FoodMart]
Checksum:[adc67095ea588fb8ef5cc174a3f74b7a]
Cube:[Sales]
Measure:[Unit Sales]
Axes:[
    {`time_by_day`.`the_year`=(*)}
    {`time_by_day`.`quarter`=(*)}
    {`product_class`.`product_family`=(*)}]
Excluded Regions:[
    {`time_by_day`.`quarter`=('Q1')}
    {`time_by_day`.`the_year`=('1997')}]
Compound Predicates:[]
ID:[9f50b66f4b4ec752bffb517748da678f9a27b778348ebac17d56026b7a4c5322]

*Segment Header
Schema:[FoodMart]
Checksum:[adc67095ea588fb8ef5cc174a3f74b7a]
Cube:[Sales]
Measure:[Unit Sales]
Axes:[
    {`time_by_day`.`the_year`=(*)}
    {`time_by_day`.`month_of_year`=(*)}
    {`product_class`.`product_family`=(*)}]
Excluded Regions:[
    {`time_by_day`.`the_year`=('1997')}]
Compound Predicates:[]
ID:[fe48ec3f27eaa745d01f2fbecbd7d4b402919c0c8284df1fde387b2335346af6]

*Segment Header
Schema:[FoodMart]
Checksum:[adc67095ea588fb8ef5cc174a3f74b7a]
Cube:[Sales]
Measure:[Unit Sales]
Axes:[
    {`time_by_day`.`the_year`=(*)}
    {`product_class`.`product_family`=(*)}]
Excluded Regions:[
    {`time_by_day`.`the_year`=('1997')}]
Compound Predicates:[]
ID:[4da974e2956637bee48be7ef4b6a766d92ba009ca69a4a7a5583d49cd4c8943c]


Cache state after flush:
*Segment Header
Schema:[FoodMart]
Checksum:[adc67095ea588fb8ef5cc174a3f74b7a]
Cube:[Sales]
Measure:[Unit Sales]
Axes:[
    {`time_by_day`.`the_year`=(*)}
    {`time_by_day`.`quarter`=(*)}
    {`product_class`.`product_family`=(*)}]
Excluded Regions:[
    {`time_by_day`.`quarter`=('Q1')}
    {`time_by_day`.`the_year`=('1997')}]
Compound Predicates:[]
ID:[9f50b66f4b4ec752bffb517748da678f9a27b778348ebac17d56026b7a4c5322]

*Segment Header
Schema:[FoodMart]
Checksum:[adc67095ea588fb8ef5cc174a3f74b7a]
Cube:[Sales]
Measure:[Unit Sales]
Axes:[
    {`time_by_day`.`the_year`=(*)}
    {`time_by_day`.`month_of_year`=(*)}
    {`product_class`.`product_family`=(*)}]
Excluded Regions:[
    {`time_by_day`.`the_year`=('1997')}]
Compound Predicates:[]
ID:[fe48ec3f27eaa745d01f2fbecbd7d4b402919c0c8284df1fde387b2335346af6]

*Segment Header
Schema:[FoodMart]
Checksum:[adc67095ea588fb8ef5cc174a3f74b7a]
Cube:[Sales]
Measure:[Unit Sales]
Axes:[
    {`time_by_day`.`the_year`=(*)}
    {`product_class`.`product_family`=(*)}]
Excluded Regions:[
    {`time_by_day`.`the_year`=('1997')}]
Compound Predicates:[]
ID:[4da974e2956637bee48be7ef4b6a766d92ba009ca69a4a7a5583d49cd4c8943c]


]]>
        </Resource>
        <Resource name="output4">
            <![CDATA[Cache state before flush:
*Segment Header
Schema:[FoodMart]
Checksum:[adc67095ea588fb8ef5cc174a3f74b7a]
Cube:[Sales]
Measure:[Unit Sales]
Axes:[
    {`time_by_day`.`the_year`=(*)}
    {`time_by_day`.`quarter`=(*)}
    {`product_class`.`product_family`=(*)}]
Excluded Regions:[
    {`time_by_day`.`quarter`=('Q1')}
    {`time_by_day`.`the_year`=('1997')}]
Compound Predicates:[]
ID:[9f50b66f4b4ec752bffb517748da678f9a27b778348ebac17d56026b7a4c5322]

*Segment Header
Schema:[FoodMart]
Checksum:[adc67095ea588fb8ef5cc174a3f74b7a]
Cube:[Sales]
Measure:[Unit Sales]
Axes:[
    {`time_by_day`.`the_year`=(*)}
    {`time_by_day`.`month_of_year`=(*)}
    {`product_class`.`product_family`=(*)}]
Excluded Regions:[
    {`time_by_day`.`the_year`=('1997')}]
Compound Predicates:[]
ID:[fe48ec3f27eaa745d01f2fbecbd7d4b402919c0c8284df1fde387b2335346af6]

*Segment Header
Schema:[FoodMart]
Checksum:[adc67095ea588fb8ef5cc174a3f74b7a]
Cube:[Sales]
Measure:[Unit Sales]
Axes:[
    {`time_by_day`.`the_year`=(*)}
    {`product_class`.`product_family`=(*)}]
Excluded Regions:[
    {`time_by_day`.`the_year`=('1997')}]
Compound Predicates:[]
ID:[4da974e2956637bee48be7ef4b6a766d92ba009ca69a4a7a5583d49cd4c8943c]


discard segment - it cannot be constrained and maintain consistency:
*Segment Header
Schema:[FoodMart]
Checksum:[adc67095ea588fb8ef5cc174a3f74b7a]
Cube:[Sales]
Measure:[Unit Sales]
Axes:[
    {`time_by_day`.`the_year`=(*)}
    {`time_by_day`.`quarter`=(*)}
    {`product_class`.`product_family`=(*)}]
Excluded Regions:[
    {`time_by_day`.`quarter`=('Q1')}
    {`time_by_day`.`the_year`=('1997')}]
Compound Predicates:[]
ID:[9f50b66f4b4ec752bffb517748da678f9a27b778348ebac17d56026b7a4c5322]

discard segment - it cannot be constrained and maintain consistency:
*Segment Header
Schema:[FoodMart]
Checksum:[adc67095ea588fb8ef5cc174a3f74b7a]
Cube:[Sales]
Measure:[Unit Sales]
Axes:[
    {`time_by_day`.`the_year`=(*)}
    {`time_by_day`.`month_of_year`=(*)}
    {`product_class`.`product_family`=(*)}]
Excluded Regions:[
    {`time_by_day`.`the_year`=('1997')}]
Compound Predicates:[]
ID:[fe48ec3f27eaa745d01f2fbecbd7d4b402919c0c8284df1fde387b2335346af6]

discard segment - it cannot be constrained and maintain consistency:
*Segment Header
Schema:[FoodMart]
Checksum:[adc67095ea588fb8ef5cc174a3f74b7a]
Cube:[Sales]
Measure:[Unit Sales]
Axes:[
    {`time_by_day`.`the_year`=(*)}
    {`product_class`.`product_family`=(*)}]
Excluded Regions:[
    {`time_by_day`.`the_year`=('1997')}]
Compound Predicates:[]
ID:[4da974e2956637bee48be7ef4b6a766d92ba009ca69a4a7a5583d49cd4c8943c]

Cache state after flush:

]]>
        </Resource>
    </TestCase>
    <TestCase name="testFlush">
        <Resource name="output">
            <![CDATA[Cache state before flush:

Cache state before flush:
*Segment Header
Schema:[FoodMart]
Checksum:[adc67095ea588fb8ef5cc174a3f74b7a]
Cube:[Sales]
Measure:[Unit Sales]
Axes:[
    {`time_by_day`.`the_year`=(*)}
    {`time_by_day`.`quarter`=(*)}
    {`product_class`.`product_family`=(*)}]
Excluded Regions:[]
Compound Predicates:[]
ID:[8a3939757ec208163e5055273052b42dff2d30427ba96d9dbc847a30b02bc33d]

*Segment Header
Schema:[FoodMart]
Checksum:[adc67095ea588fb8ef5cc174a3f74b7a]
Cube:[Sales]
Measure:[Unit Sales]
Axes:[
    {`time_by_day`.`the_year`=(*)}
    {`time_by_day`.`month_of_year`=(*)}
    {`product_class`.`product_family`=(*)}]
Excluded Regions:[]
Compound Predicates:[]
ID:[96d7e3c62da4423e048b87cb83dd06fc3b19223d8f9d9c95e9169f292dd29cb5]

*Segment Header
Schema:[FoodMart]
Checksum:[adc67095ea588fb8ef5cc174a3f74b7a]
Cube:[Sales]
Measure:[Unit Sales]
Axes:[
    {`time_by_day`.`the_year`=(*)}
    {`product_class`.`product_family`=(*)}]
Excluded Regions:[]
Compound Predicates:[]
ID:[4a078bc2e0f7d362dc7b9f3ff775166cc40ba5a040af5fe11c43d8c1a4d8a832]


Cache state after flush:
*Segment Header
Schema:[FoodMart]
Checksum:[adc67095ea588fb8ef5cc174a3f74b7a]
Cube:[Sales]
Measure:[Unit Sales]
Axes:[
    {`time_by_day`.`the_year`=(*)}
    {`time_by_day`.`quarter`=(*)}
    {`product_class`.`product_family`=(*)}]
Excluded Regions:[
    {`time_by_day`.`quarter`=('Q1')}
    {`time_by_day`.`the_year`=('1997')}
    {`product_class`.`product_family`=('Drink')}]
Compound Predicates:[]
ID:[a978b9f1e35786873193579a0456b6add2ac9b078bf183c73b244227b6eb9532]

*Segment Header
Schema:[FoodMart]
Checksum:[adc67095ea588fb8ef5cc174a3f74b7a]
Cube:[Sales]
Measure:[Unit Sales]
Axes:[
    {`time_by_day`.`the_year`=(*)}
    {`time_by_day`.`month_of_year`=(*)}
    {`product_class`.`product_family`=(*)}]
Excluded Regions:[
    {`time_by_day`.`the_year`=('1997')}
    {`product_class`.`product_family`=('Drink')}]
Compound Predicates:[]
ID:[d5abfbed4de4fb74b9d3b3224f503ce2789910c1f5191c0a020a828e02bf8771]

*Segment Header
Schema:[FoodMart]
Checksum:[adc67095ea588fb8ef5cc174a3f74b7a]
Cube:[Sales]
Measure:[Unit Sales]
Axes:[
    {`time_by_day`.`the_year`=(*)}
    {`product_class`.`product_family`=(*)}]
Excluded Regions:[
    {`time_by_day`.`the_year`=('1997')}
    {`product_class`.`product_family`=('Drink')}]
Compound Predicates:[]
ID:[f32e2d6ce94cc5264885b0951d8406ea064b2d2029228c1459b42f9d49337a18]


]]>
        </Resource>
        <Resource name="output2">
            <![CDATA[*Segment Header
Schema:[FoodMart]
Checksum:[adc67095ea588fb8ef5cc174a3f74b7a]
Cube:[Sales]
Measure:[Unit Sales]
Axes:[
    {`time_by_day`.`the_year`=(*)}
    {`time_by_day`.`quarter`=(*)}
    {`product_class`.`product_family`=(*)}]
Excluded Regions:[]
Compound Predicates:[]
ID:[8a3939757ec208163e5055273052b42dff2d30427ba96d9dbc847a30b02bc33d]

*Segment Header
Schema:[FoodMart]
Checksum:[adc67095ea588fb8ef5cc174a3f74b7a]
Cube:[Sales]
Measure:[Unit Sales]
Axes:[
    {`time_by_day`.`the_year`=(*)}
    {`time_by_day`.`quarter`=(*)}
    {`product_class`.`product_family`=(*)}]
Excluded Regions:[
    {`time_by_day`.`quarter`=('Q1')}
    {`time_by_day`.`the_year`=('1997')}
    {`product_class`.`product_family`=('Drink')}]
Compound Predicates:[]
ID:[a978b9f1e35786873193579a0456b6add2ac9b078bf183c73b244227b6eb9532]

*Segment Header
Schema:[FoodMart]
Checksum:[adc67095ea588fb8ef5cc174a3f74b7a]
Cube:[Sales]
Measure:[Unit Sales]
Axes:[
    {`time_by_day`.`the_year`=(*)}
    {`time_by_day`.`month_of_year`=(*)}
    {`product_class`.`product_family`=(*)}]
Excluded Regions:[]
Compound Predicates:[]
ID:[96d7e3c62da4423e048b87cb83dd06fc3b19223d8f9d9c95e9169f292dd29cb5]

*Segment Header
Schema:[FoodMart]
Checksum:[adc67095ea588fb8ef5cc174a3f74b7a]
Cube:[Sales]
Measure:[Unit Sales]
Axes:[
    {`time_by_day`.`the_year`=(*)}
    {`time_by_day`.`month_of_year`=(*)}
    {`product_class`.`product_family`=(*)}]
Excluded Regions:[
    {`time_by_day`.`the_year`=('1997')}
    {`product_class`.`product_family`=('Drink')}]
Compound Predicates:[]
ID:[d5abfbed4de4fb74b9d3b3224f503ce2789910c1f5191c0a020a828e02bf8771]

*Segment Header
Schema:[FoodMart]
Checksum:[adc67095ea588fb8ef5cc174a3f74b7a]
Cube:[Sales]
Measure:[Unit Sales]
Axes:[
    {`time_by_day`.`the_year`=(*)}
    {`product_class`.`product_family`=(*)}]
Excluded Regions:[
    {`time_by_day`.`the_year`=('1997')}
    {`product_class`.`product_family`=('Drink')}]
Compound Predicates:[]
ID:[f32e2d6ce94cc5264885b0951d8406ea064b2d2029228c1459b42f9d49337a18]

*Segment Header
Schema:[FoodMart]
Checksum:[adc67095ea588fb8ef5cc174a3f74b7a]
Cube:[Sales]
Measure:[Unit Sales]
Axes:[
    {`time_by_day`.`the_year`=(*)}
    {`product_class`.`product_family`=(*)}]
Excluded Regions:[]
Compound Predicates:[]
ID:[4a078bc2e0f7d362dc7b9f3ff775166cc40ba5a040af5fe11c43d8c1a4d8a832]

]]>
        </Resource>
    </TestCase>
    <TestCase name="testPartialFlushRange">
        <Resource name="output">
            <![CDATA[Cache state before flush:
*Segment Header
Schema:[FoodMart]
Checksum:[adc67095ea588fb8ef5cc174a3f74b7a]
Cube:[Sales]
Measure:[Unit Sales]
Axes:[
    {`time_by_day`.`the_year`=(*)}
    {`time_by_day`.`quarter`=(*)}
    {`product_class`.`product_family`=(*)}]
Excluded Regions:[]
Compound Predicates:[]
ID:[8a3939757ec208163e5055273052b42dff2d30427ba96d9dbc847a30b02bc33d]

*Segment Header
Schema:[FoodMart]
Checksum:[adc67095ea588fb8ef5cc174a3f74b7a]
Cube:[Sales]
Measure:[Unit Sales]
Axes:[
    {`time_by_day`.`the_year`=(*)}
    {`time_by_day`.`month_of_year`=(*)}
    {`product_class`.`product_family`=(*)}]
Excluded Regions:[]
Compound Predicates:[]
ID:[96d7e3c62da4423e048b87cb83dd06fc3b19223d8f9d9c95e9169f292dd29cb5]

*Segment Header
Schema:[FoodMart]
Checksum:[adc67095ea588fb8ef5cc174a3f74b7a]
Cube:[Sales]
Measure:[Unit Sales]
Axes:[
    {`time_by_day`.`the_year`=(*)}
    {`product_class`.`product_family`=(*)}]
Excluded Regions:[]
Compound Predicates:[]
ID:[4a078bc2e0f7d362dc7b9f3ff775166cc40ba5a040af5fe11c43d8c1a4d8a832]


discard segment - it cannot be constrained and maintain consistency:
*Segment Header
Schema:[FoodMart]
Checksum:[adc67095ea588fb8ef5cc174a3f74b7a]
Cube:[Sales]
Measure:[Unit Sales]
Axes:[
    {`time_by_day`.`the_year`=(*)}
    {`time_by_day`.`quarter`=(*)}
    {`product_class`.`product_family`=(*)}]
Excluded Regions:[]
Compound Predicates:[]
ID:[8a3939757ec208163e5055273052b42dff2d30427ba96d9dbc847a30b02bc33d]

discard segment - it cannot be constrained and maintain consistency:
*Segment Header
Schema:[FoodMart]
Checksum:[adc67095ea588fb8ef5cc174a3f74b7a]
Cube:[Sales]
Measure:[Unit Sales]
Axes:[
    {`time_by_day`.`the_year`=(*)}
    {`time_by_day`.`month_of_year`=(*)}
    {`product_class`.`product_family`=(*)}]
Excluded Regions:[]
Compound Predicates:[]
ID:[96d7e3c62da4423e048b87cb83dd06fc3b19223d8f9d9c95e9169f292dd29cb5]

discard segment - it cannot be constrained and maintain consistency:
*Segment Header
Schema:[FoodMart]
Checksum:[adc67095ea588fb8ef5cc174a3f74b7a]
Cube:[Sales]
Measure:[Unit Sales]
Axes:[
    {`time_by_day`.`the_year`=(*)}
    {`product_class`.`product_family`=(*)}]
Excluded Regions:[]
Compound Predicates:[]
ID:[4a078bc2e0f7d362dc7b9f3ff775166cc40ba5a040af5fe11c43d8c1a4d8a832]

Cache state after flush:

]]>
        </Resource>
        <Resource name="output2">
            <![CDATA[Cache state before flush:

Cache state after flush:

]]>
        </Resource>
        <Resource name="output3">
            <![CDATA[*Segment Header
Schema:[FoodMart]
Checksum:[adc67095ea588fb8ef5cc174a3f74b7a]
Cube:[Sales]
Measure:[Unit Sales]
Axes:[
    {`time_by_day`.`the_year`=(*)}
    {`time_by_day`.`quarter`=(*)}
    {`product_class`.`product_family`=(*)}]
Excluded Regions:[]
Compound Predicates:[]
ID:[8a3939757ec208163e5055273052b42dff2d30427ba96d9dbc847a30b02bc33d]

*Segment Header
Schema:[FoodMart]
Checksum:[adc67095ea588fb8ef5cc174a3f74b7a]
Cube:[Sales]
Measure:[Unit Sales]
Axes:[
    {`time_by_day`.`the_year`=(*)}
    {`time_by_day`.`month_of_year`=(*)}
    {`product_class`.`product_family`=(*)}]
Excluded Regions:[]
Compound Predicates:[]
ID:[96d7e3c62da4423e048b87cb83dd06fc3b19223d8f9d9c95e9169f292dd29cb5]

*Segment Header
Schema:[FoodMart]
Checksum:[adc67095ea588fb8ef5cc174a3f74b7a]
Cube:[Sales]
Measure:[Unit Sales]
Axes:[
    {`time_by_day`.`the_year`=(*)}
    {`product_class`.`product_family`=(*)}]
Excluded Regions:[]
Compound Predicates:[]
ID:[4a078bc2e0f7d362dc7b9f3ff775166cc40ba5a040af5fe11c43d8c1a4d8a832]

]]>
        </Resource>
    </TestCase>
</Root>
